mobot/__init__.py
mobot/_proto/__init__.py
mobot/_proto/accelerometer_pb2.py
mobot/_proto/accelerometer_pb2_grpc.py
mobot/_proto/camera_pb2.py
mobot/_proto/camera_pb2_grpc.py
mobot/_proto/chassis_pb2.py
mobot/_proto/chassis_pb2_grpc.py
mobot/_proto/common_pb2.py
mobot/_proto/common_pb2_grpc.py
mobot/_proto/connection_pb2.py
mobot/_proto/connection_pb2_grpc.py
mobot/_proto/flashlight_pb2.py
mobot/_proto/flashlight_pb2_grpc.py
mobot/_proto/gyroscope_pb2.py
mobot/_proto/gyroscope_pb2_grpc.py
mobot/_proto/imu_pb2.py
mobot/_proto/imu_pb2_grpc.py
mobot/_proto/listen_pb2.py
mobot/_proto/listen_pb2_grpc.py
mobot/_proto/magnetometer_pb2.py
mobot/_proto/magnetometer_pb2_grpc.py
mobot/_proto/speak_pb2.py
mobot/_proto/speak_pb2_grpc.py
mobot/_proto/talk_pb2.py
mobot/_proto/talk_pb2_grpc.py
mobot/_spine/__init__.py
mobot/_spine/connection.py
mobot/_spine/server.py
mobot/_tests/__init__.py
mobot/_tests/accelerometer_test.py
mobot/_tests/camera_test.py
mobot/_tests/chassis_test.py
mobot/_tests/flashlight_test.py
mobot/_tests/gyroscope_test.py
mobot/_tests/magnetometer_test.py
mobot/_tests/performance_test.py
mobot/brain/__init__.py
mobot/brain/_connection.py
mobot/brain/_exceptions.py
mobot/brain/agent.py
mobot/brain/assets/__init__.py
mobot/brain/assets/accelerometer.py
mobot/brain/assets/camera.py
mobot/brain/assets/chassis.py
mobot/brain/assets/flashlight.py
mobot/brain/assets/gyroscope.py
mobot/brain/assets/listen.py
mobot/brain/assets/magnetometer.py
mobot/brain/assets/speak.py
mobot/brain/assets/abstract/__init__.py
mobot/brain/assets/abstract/actuator.py
mobot/brain/assets/abstract/asset.py
mobot/brain/assets/abstract/sensor.py
mobot/utils/__init__.py
mobot/utils/logging.py
mobot/utils/network.py
mobot/utils/rate.py
mobot-0.1.2.dist-info/METADATA
mobot-0.1.2.dist-info/WHEEL
mobot-0.1.2.dist-info/entry_points.txt
mobot-0.1.2.dist-info/top_level.txt
mobot-0.1.2.dist-info/RECORD
