Metadata-Version: 2.1
Name: mobot
Version: 0.1.2
Summary: Turning Mobile Phone into Robot
Home-page: https://github.com/mobotx/mobot
Author: Aditya Shriwastava
Author-email: adityashriwastava7@gmail.com
License: UNKNOWN
Platform: UNKNOWN
Classifier: Programming Language :: Python :: 3
Classifier: License :: OSI Approved :: MIT License
Classifier: Operating System :: OS Independent
Requires-Python: >=3.6
Requires-Dist: grpcio
Requires-Dist: numpy
Requires-Dist: Pillow
Requires-Dist: texttable
